autoapi/__init__.py
autoapi/generators.py
autoapi/settings.py
autoapi/urls.py
autoapi/utils.py
autoapi/views.py
djangoautoapi-0.0.1.dist-info/LICENSE.md
djangoautoapi-0.0.1.dist-info/METADATA
djangoautoapi-0.0.1.dist-info/WHEEL
djangoautoapi-0.0.1.dist-info/top_level.txt
djangoautoapi-0.0.1.dist-info/RECORD
