Metadata-Version: 2.1
Name: djangoautoapi
Version: 0.0.1
Summary: Automatic REST API Creation
Home-page: https://github.com/z1digitalstudio/djangoautoapi
Author: Emilio A. Sanchez
Author-email: emilio@commite.co
License: BSD
Platform: UNKNOWN
Classifier: Development Status :: 3 - Alpha
Classifier: Environment :: Web Environment
Classifier: Framework :: Django
Classifier: Framework :: Django :: 2.1
Classifier: Framework :: Django :: 2.2
Classifier: Intended Audience :: Developers
Classifier: License :: OSI Approved :: BSD License
Classifier: Operating System :: OS Independent
Classifier: Programming Language :: Python
Classifier: Programming Language :: Python :: 3.6
Classifier: Programming Language :: Python :: 3.7
Classifier: Topic :: Internet :: WWW/HTTP
Requires-Python: >=3.6
